flask_rings/__init__.py
flask_rings/static/css/rings.min.css
flask_rings/templates/rings/nav.html
flask_rings/templates/rings/utils.html
flask_rings/templates/rings/wtf.html
Flask_Rings-0.4.2.dist-info/LICENSE
Flask_Rings-0.4.2.dist-info/METADATA
Flask_Rings-0.4.2.dist-info/WHEEL
Flask_Rings-0.4.2.dist-info/top_level.txt
Flask_Rings-0.4.2.dist-info/RECORD
