Metadata-Version: 2.1
Name: Flask-Rings
Version: 0.4.2
Summary: Rings(https://github.com/ringsings/Rings) helper for flask.
Home-page: https://github.com/ringsings/flask-rings
Author: Andy Zhou
Author-email: zhoutianyou11@gmail.com
License: LGPL-3.0
Keywords: flask extension development rings
Platform: any
Classifier: Intended Audience :: Developers
Classifier: Programming Language :: Python :: 3.6
Classifier: Programming Language :: Python :: 3.7
Classifier: Programming Language :: Python
Classifier: Programming Language :: Python :: 3.8
Classifier: Environment :: Web Environment
Classifier: Programming Language :: Python :: 3.9
Classifier: Topic :: Software Development :: Libraries :: Python Modules
Classifier: Topic :: Internet :: WWW/HTTP :: Dynamic Content
Requires-Dist: Flask
Requires-Dist: Flask-WTF
